projectpy/__init__.py
projectpy/cli.py
projectpy/config.py
projectpy/utils.py
projectpy/version.py
projectpy-0.1.1.dist-info/LICENSE
projectpy-0.1.1.dist-info/METADATA
projectpy-0.1.1.dist-info/WHEEL
projectpy-0.1.1.dist-info/entry_points.txt
projectpy-0.1.1.dist-info/top_level.txt
projectpy-0.1.1.dist-info/RECORD
