Metadata-Version: 2.1
Name: projectpy
Version: 0.1.1
Summary: CLI tool to create-python-packages
Home-page: https://github.com/DumbMachine/create-python-project
Author: Ratin Kumar
Author-email: ratin.kumar.2k@gmail.com
Maintainer: Ratin Kumar (@DumbMachine)
Maintainer-email: ratin.kumar.2k@gmail.com
License: unlicensed
Download-URL: https://github.com/DumbMachine/create-python-project/releases
Platform: Any
Classifier: Development Status :: 3 - Alpha
Classifier: Intended Audience :: Developers
Classifier: Intended Audience :: Information Technology
Classifier: Intended Audience :: Science/Research
Classifier: License :: OSI Approved :: BSD License
Classifier: Operating System :: MacOS
Classifier: Operating System :: POSIX
Classifier: Operating System :: Unix
Classifier: Programming Language :: Python
Classifier: Programming Language :: Python :: 2.7
Classifier: Programming Language :: Python :: 3.4
Classifier: Programming Language :: Python :: 3.5
Classifier: Programming Language :: Python :: 3.6
Classifier: Programming Language :: Python :: 3.7
Classifier: Topic :: Software Development
Classifier: Topic :: Utilities
Requires-Dist: colorama (>=0.4.0)
Requires-Dist: pathlib
